dl85Optimizer.cpython-36m-darwin.so
dl85/__init__.py
dl85/_version.py
dl85/errors/__init__.py
dl85/errors/errors.py
dl85/predictors/__init__.py
dl85/predictors/predictor.py
dl85/supervised/__init__.py
dl85/supervised/classifiers/__init__.py
dl85/supervised/classifiers/classifier.py
dl85/supervised/classifiers/tests/__init__.py
dl85/supervised/classifiers/tests/test_DL85Classifier.py
dl85/unsupervised/__init__.py
dl85/unsupervised/clustering.py
dl8.5-0.0.10.dist-info/LICENSE.txt
dl8.5-0.0.10.dist-info/METADATA
dl8.5-0.0.10.dist-info/WHEEL
dl8.5-0.0.10.dist-info/top_level.txt
dl8.5-0.0.10.dist-info/zip-safe
dl8.5-0.0.10.dist-info/RECORD
